aws_s3_url2uri/__init__.py
aws_s3_url2uri/main.py
aws_s3_url2uri-0.1.3.dist-info/DESCRIPTION.rst
aws_s3_url2uri-0.1.3.dist-info/METADATA
aws_s3_url2uri-0.1.3.dist-info/RECORD
aws_s3_url2uri-0.1.3.dist-info/WHEEL
aws_s3_url2uri-0.1.3.dist-info/entry_points.txt
aws_s3_url2uri-0.1.3.dist-info/metadata.json
aws_s3_url2uri-0.1.3.dist-info/top_level.txt
tests/__init__.py
tests/test_main.py
