Metadata-Version: 2.0
Name: aws-s3-url2uri
Version: 0.1.3
Summary: Make awscli s3 commands work with URL
Home-page: https://github.com/keisuke-nakata/aws-cli-s3-url2uri
Author: NAKATA Keisuke
Author-email: keisuke.nakata.919@gmail.com
License: Apache License 2.0
Platform: UNKNOWN
Requires-Dist: awscli
Requires-Dist: click
